odoo/addons/sale_commission_product_criteria_country/README.rst
odoo/addons/sale_commission_product_criteria_country/__init__.py
odoo/addons/sale_commission_product_criteria_country/__manifest__.py
odoo/addons/sale_commission_product_criteria_country/i18n/es.po
odoo/addons/sale_commission_product_criteria_country/i18n/it.po
odoo/addons/sale_commission_product_criteria_country/i18n/pt_BR.po
odoo/addons/sale_commission_product_criteria_country/i18n/sale_commission_product_criteria_country.pot
odoo/addons/sale_commission_product_criteria_country/models/__init__.py
odoo/addons/sale_commission_product_criteria_country/models/account_invoice_line_agent.py
odoo/addons/sale_commission_product_criteria_country/models/commission_item.py
odoo/addons/sale_commission_product_criteria_country/models/commission_line_mixin.py
odoo/addons/sale_commission_product_criteria_country/models/sale_order_line_agent.py
odoo/addons/sale_commission_product_criteria_country/readme/CONTRIBUTORS.md
odoo/addons/sale_commission_product_criteria_country/readme/DESCRIPTION.md
odoo/addons/sale_commission_product_criteria_country/readme/USAGE.md
odoo/addons/sale_commission_product_criteria_country/static/description/icon.png
odoo/addons/sale_commission_product_criteria_country/static/description/icon.svg
odoo/addons/sale_commission_product_criteria_country/static/description/index.html
odoo/addons/sale_commission_product_criteria_country/tests/__init__.py
odoo/addons/sale_commission_product_criteria_country/tests/test_sale_commission_product_criteria_country.py
odoo/addons/sale_commission_product_criteria_country/views/commission_item_views.xml
odoo_addon_sale_commission_product_criteria_country-16.0.1.0.0.5.dist-info/METADATA
odoo_addon_sale_commission_product_criteria_country-16.0.1.0.0.5.dist-info/WHEEL
odoo_addon_sale_commission_product_criteria_country-16.0.1.0.0.5.dist-info/top_level.txt
odoo_addon_sale_commission_product_criteria_country-16.0.1.0.0.5.dist-info/RECORD
