Metadata-Version: 2.1
Name: odoo-addon-sale_commission_product_criteria_country
Version: 16.0.1.0.0.5
Summary: Sale Commission Product Criteria Country
Home-page: https://github.com/OCA/commission
Author: Sygel, Odoo Community Association (OCA)
Author-email: support@odoo-community.org
License: AGPL-3
Classifier: Programming Language :: Python
Classifier: Framework :: Odoo
Classifier: Framework :: Odoo :: 16.0
Classifier: License :: OSI Approved :: GNU Affero General Public License v3
Requires-Python: >=3.10
Requires-Dist: odoo-addon-sale-commission-product-criteria<16.1dev,>=16.0dev
Requires-Dist: odoo<16.1dev,>=16.0a
